oscillatorlookups/__init__.py
oscillatorlookups/lookups.py
oscillatorlookups-1.8.3.dist-info/licenses/LICENSE
oscillatorlookups-1.8.3.dist-info/METADATA
oscillatorlookups-1.8.3.dist-info/WHEEL
oscillatorlookups-1.8.3.dist-info/top_level.txt
oscillatorlookups-1.8.3.dist-info/RECORD
