Metadata-Version: 2.4
Name: oscillatorlookups
Version: 1.8.3
Summary: Lookup operations for oscillator database
Author: Matthew Epshtein
Author-email: <epshteinmatthew@gmail.com>
Keywords: python,first package
Classifier: Development Status :: 5 - Production/Stable
Classifier: Intended Audience :: Education
Classifier: Programming Language :: Python :: 2
Classifier: Programming Language :: Python :: 3
Classifier: Operating System :: MacOS :: MacOS X
Classifier: Operating System :: Microsoft :: Windows
License-File: LICENSE
Requires-Dist: aiohttp
Requires-Dist: aiofiles
Requires-Dist: msgspec
Dynamic: author
Dynamic: author-email
Dynamic: classifier
Dynamic: description
Dynamic: keywords
Dynamic: license-file
Dynamic: requires-dist
Dynamic: summary
